MANIFEST.in
README.rst
setup.cfg
setup.py
beaver_sqs/__init__.py
beaver_sqs.egg-info/PKG-INFO
beaver_sqs.egg-info/SOURCES.txt
beaver_sqs.egg-info/dependency_links.txt
beaver_sqs.egg-info/requires.txt
beaver_sqs.egg-info/top_level.txt