Metadata-Version: 1.1
Name: beaver-sqs
Version: 0.0.1
Summary: python daemon that munches on logs and sends their contents to logstash
Home-page: http://github.com/python-beaver/beaver-sqs
Author: Jamie Cressey
Author-email: jamiecressey89@gmail.com
License: LICENSE.txt
Platform: UNKNOWN
Classifier: Development Status :: 5 - Production/Stable
Classifier: Intended Audience :: System Administrators
Classifier: License :: OSI Approved :: MIT License
Classifier: Programming Language :: Python :: 2.6
Classifier: Programming Language :: Python :: 2.7
Classifier: Topic :: System :: Logging
